odoo8_addon_mail_debrand-8.0.1.0.2-py2.7-nspkg.pth
odoo8_addon_mail_debrand-8.0.1.0.2.dist-info/DESCRIPTION.rst
odoo8_addon_mail_debrand-8.0.1.0.2.dist-info/METADATA
odoo8_addon_mail_debrand-8.0.1.0.2.dist-info/RECORD
odoo8_addon_mail_debrand-8.0.1.0.2.dist-info/WHEEL
odoo8_addon_mail_debrand-8.0.1.0.2.dist-info/metadata.json
odoo8_addon_mail_debrand-8.0.1.0.2.dist-info/namespace_packages.txt
odoo8_addon_mail_debrand-8.0.1.0.2.dist-info/top_level.txt
odoo_addons/mail_debrand/README.rst
odoo_addons/mail_debrand/__init__.py
odoo_addons/mail_debrand/__openerp__.py
odoo_addons/mail_debrand/i18n/de.po
odoo_addons/mail_debrand/i18n/el_GR.po
odoo_addons/mail_debrand/i18n/es.po
odoo_addons/mail_debrand/i18n/fi.po
odoo_addons/mail_debrand/i18n/fr.po
odoo_addons/mail_debrand/i18n/it.po
odoo_addons/mail_debrand/i18n/nl.po
odoo_addons/mail_debrand/i18n/sl.po
odoo_addons/mail_debrand/models/__init__.py
odoo_addons/mail_debrand/models/mail.py
odoo_addons/mail_debrand/static/description/icon.png
odoo_addons/mail_debrand/tests/__init__.py
odoo_addons/mail_debrand/tests/test_mail.py
